notmuch_sync.py
notmuch_sync-0.0.3.dist-info/METADATA
notmuch_sync-0.0.3.dist-info/WHEEL
notmuch_sync-0.0.3.dist-info/entry_points.txt
notmuch_sync-0.0.3.dist-info/licenses/LICENSE
notmuch_sync-0.0.3.dist-info/RECORD
